[
   {"pack":1,
    "name": "Backpack",
    "type": "backpacks",
    "desc":"Not required for all students",
    "required":1,
    "school":"MAES",
    "grade":"7"
  },
  {"pack":1,
    "name": "Headphones/earbuds",
    "type": "headphones",
    "desc":"Good quality, REQUIRED",
    "required":1,
    "school":"MAES",
    "grade":"7"
  },
  {"pack":1,
    "name": "Grocery bag/brown paper",
    "type": "other",
    "desc":"For textbook cover",
    "required":2,
    "school":"MAES",
    "grade":"7"
  },
  {"pack":1,
    "name": "Pencils",
    "type": "pencils",
    "desc":"#2, Yellow",
    "required":6,
    "school":"MAES",
    "grade":"7"
  },
  {"pack":1,
    "name": "Pens",
    "type": "pens",
    "desc":"Black or blue only",
    "required":12,
    "school":"MAES",
    "grade":"7"
  },
  {"pack":1,
    "name": "Highlighter",
    "type": "highlighters",
    "desc":"any color",
    "required":2,
    "school":"MAES",
    "grade":"7"
  },
  {"pack":1,
    "name": "Colored Pencil",
    "type": "pencils",
    "desc":"7th Graders only",
    "required":2,
    "school":"MAES",
    "grade":"7"
  },
  {"pack":12,
    "name": "Markers",
    "type": "markers",
    "desc":"7th Graders only",
    "required":1,
    "school":"MAES",
    "grade":"7"
  },
  {"pack":12,
    "name": "Crayons",
    "type": "crayons",
    "desc":"7th Graders only",
    "required":1,
    "school":"MAES",
    "grade":"7"
  },
  {"pack":1,
    "name": "Glue Sticks",
    "type": "glue",
    "desc":"",
    "required":6,
    "school":"MAES",
    "grade":"7"
  },
  {"pack":1,
    "name": "Scissors",
    "type": "scissors",
    "desc":"7-inch only",
    "required":1,
    "school":"MAES",
    "grade":"7"
  },
  {"pack":5,
    "name": "Colored Folders",
    "type": "folders",
    "desc":"Red, Green, Purple, Yellow, and Blue.",
    "required":1,
    "school":"MAES",
    "grade":"7"
  },
  {"pack":5,
    "name": "Colored Notebooks",
    "type": "notebooks",
    "desc":"Red, Green, Purple, Yellow, and Blue",
    "required":1,
    "school":"MAES",
    "grade":"7"
  },
  {"pack":1,
    "name": "Composition Notebook",
    "type": "notebooks",
    "desc":"7th grade only",
    "required":1,
    "school":"MAES",
    "grade":"7"
  },
  {"pack":200,
    "name": "Loose Leaf Paper",
    "type": "other",
    "desc":"",
    "required":1,
    "school":"MAES",
    "grade":"7"
  },
  {"pack":1,
    "name": "Backpack",
    "type": "backpacks",
    "desc":"Not required for all students",
    "required":1,
    "school":"MAES",
    "grade":"6"
  },
  {"pack":1,
    "name": "Headphones/earbuds",
    "type": "headphones",
    "desc":"Good quality, REQUIRED",
    "required":1,
    "school":"MAES",
    "grade":"6"
  },
  {"pack":36,
  "name": "Pencils",
  "type": "pencils",
  "desc":"Any variety",
  "required":1,
  "school":"MAES",
  "grade":"6"
  },
  {"pack":1,
  "name": "Pens",
  "type": "pens",
  "desc":"Blue or black",
  "required":2,
  "school":"MAES",
  "grade":"6"
  },
  {"pack":1,
  "name": "Pen",
  "type": "pens",
  "desc":"Red",
  "required":1,
  "school":"MAES",
  "grade":"6"
  },
  {"pack":1,
  "name": "Eraser",
  "type": "erasers",
  "desc":"",
  "required":1,
  "school":"MAES",
  "grade":"6"
  },
  {"pack":1,
  "name": "Highlighters",
  "type": "highlighters",
  "desc":"Any color",
  "required":2,
  "school":"MAES",
  "grade":"6"
  },
  {"pack":12,
  "name": "Colored Pencils",
  "type": "colored_pencils",
  "desc":"12 or 24 pack",
  "required":1,
  "school":"MAES",
  "grade":"6"
  },
  {"pack":1,
  "name": "Dry Erase Markers",
  "type": "dry_erase_markers",
  "desc":"Expo only, black",
  "required":2,
  "school":"MAES",
  "grade":"6"
  },
  {"pack":1,
  "name": "Glue Stick",
  "type": "glue",
  "desc":"",
  "required":1,
  "school":"MAES",
  "grade":"6"
  },
  {"pack":1,
  "name": "Scissors",
  "type": "scissors",
  "desc":"",
  "required":1,
  "school":"MAES",
  "grade":"6"
  },
    {"pack":5,
    "name": "Colored Notebooks",
    "type": "notebooks",
    "desc":"Red, Green, Purple, Yellow, and Blue",
    "required":1,
    "school":"MAES",
    "grade":"6"
  },
  {"pack":1,
  "name": "Post-It Notes",
  "type": "other",
  "desc":"Standard size",
  "required":1,
  "school":"MAES",
  "grade":"6"
  },
  {"pack":1,
  "name": "3-Ring Binder",
  "type": "binders",
  "desc":"1-inch, with front cover pocket",
  "required":1,
  "school":"MAES",
  "grade":"6"
  },
  {"pack":5,
    "name": "Colored Folders",
    "type": "folders",
    "desc":"Red, Green, Purple, Yellow, and Blue.",
    "required":1,
    "school":"MAES",
    "grade":"6"
  },
  {"pack":50,
    "name": "Page Protectors",
    "type": "other",
    "desc":"Plastic",
    "required":1,
    "school":"MAES",
    "grade":"6"
  },
  {"pack":100,
    "name": "Index Cards",
    "type": "other",
    "desc":"3x5in, lined",
    "required":1,
    "school":"MAES",
    "grade":"6"
  },
  {"pack":1,
    "name": "Tennis Shoes",
    "type": "other",
    "desc":"For phy. ed.",
    "required":1,
    "school":"MAES",
    "grade":"6"
  },
  {"pack":1,
    "name": "Computer Mouse",
    "type": "other",
    "desc":"(Recommended)",
    "required":1,
    "school":"MAES",
    "grade":"6"
  },
  {"pack":200,
    "name": "Kleenex",
    "type": "other",
    "desc":"",
    "required":3,
    "school":"MAES",
    "grade":"6"
  },
  {"pack":1,
    "name": "Bleach Wipes",
    "type": "other",
    "desc":"Clorox",
    "required":2,
    "school":"MAES",
    "grade":"6"
  },
  {"pack":1,
    "name": "Backpack",
    "type": "backpacks",
    "desc":"Not required for all students",
    "required":1,
    "school":"MAES",
    "grade":"5"
  },
  {"pack":1,
    "name": "Headphones/earbuds",
    "type": "headphones",
    "desc":"Good quality, REQUIRED",
    "required":1,
    "school":"MAES",
    "grade":"5"
  },
  {"pack":1,
    "name": "Pencil Box",
    "type": "boxes",
    "desc":"",
    "required":1,
    "school":"MAES",
    "grade":"5"
  },
  {"pack":24,
    "name": "Pencils",
    "type": "pencils",
    "desc":"#2 Only",
    "required":1,
    "school":"MAES",
    "grade":"5"
  },
  {"pack":1,
    "name": "Highlighter",
    "type": "highlighters",
    "desc":"Any Color",
    "required":1,
    "school":"MAES",
    "grade":"5"
  },
  {"pack":12,
    "name": "Colored Pencils",
    "type": "colored_pencils",
    "desc":"12 or 24 pack",
    "required":1,
    "school":"MAES",
    "grade":"5"
  },
  {"pack":1,
    "name": "Markers",
    "type": "markers",
    "desc":"",
    "required":1,
    "school":"MAES",
    "grade":"5"
  },
  {"pack":1,
    "name": "Sharpie",
    "type": "markers",
    "desc":"Regular size",
    "required":2,
    "school":"MAES",
    "grade":"5"
  },
  {"pack":1,
    "name": "Dry Erase Markers",
    "type": "dry_erase_markers",
    "desc":"Expo only, black",
    "required":8,
    "school":"MAES",
    "grade":"5"
  },
  {"pack":1,
    "name": "Elmer's Glue",
    "type": "glue",
    "desc":"Bottled",
    "required":1,
    "school":"MAES",
    "grade":"5"
  },
  {"pack":1,
    "name": "Glue Stick",
    "type": "glue",
    "desc":"",
    "required":4,
    "school":"MAES",
    "grade":"5"
  },
  {"pack":1,
    "name": "Glue Stick",
    "type": "glue",
    "desc":"",
    "required":4,
    "school":"MAES",
    "grade":"5"
  },
  {"pack":1,
    "name": "Scissors",
    "type": "scissors",
    "desc":"",
    "required":1,
    "school":"MAES",
    "grade":"5"
  },
  {"pack":1,
    "name": "Spiral Notebook",
    "type": "notebooks",
    "desc":"One Subject",
    "required":1,
    "school":"MAES",
    "grade":"5"
  },
  {"pack":1,
    "name": "3-Ring Binder",
    "type": "binders",
    "desc":"1-inch, with front cover pocket",
    "required":1,
    "school":"MAES",
    "grade":"5"
  },
  {"pack":5,
    "name": "Colored Folders",
    "type": "folders",
    "desc":"Red, Green, Purple, Yellow, and Blue.",
    "required":1,
    "school":"MAES",
    "grade":"5"
  },
  {"pack":100,
    "name": "Index Cards",
    "type": "other",
    "desc":"3x5in, lined",
    "required":1,
    "school":"MAES",
    "grade":"5"
  },
  {"pack":1,
    "name": "Tennis Shoes",
    "type": "other",
    "desc":"For phy. ed.",
    "required":1,
    "school":"MAES",
    "grade":"5"
  },
  {"pack":1,
    "name": "Computer Mouse",
    "type": "other",
    "desc":"(Recommended)",
    "required":1,
    "school":"MAES",
    "grade":"5"
  },
  {"pack":200,
    "name": "Kleenex",
    "type": "other",
    "desc":"",
    "required":3,
    "school":"MAES",
    "grade":"5"
  },
  {"pack":1,
    "name": "Bleach Wipes",
    "type": "other",
    "desc":"Clorox",
    "required":2,
    "school":"MAES",
    "grade":"5"
  },
  {"pack":1,
    "name": "Backpack",
    "type": "backpacks",
    "desc":"Not required for all students",
    "required":1,
    "school":"MAES",
    "grade":"4"
  },
  {"pack":1,
    "name": "Headphones/earbuds",
    "type": "headphones",
    "desc":"Good quality, NOT BLUETOOTH",
    "required":1,
    "school":"MAES",
    "grade":"4"
  },
  {"pack":1,
    "name": "Pencil Box",
    "type": "boxes",
    "desc":"Average size, (ie, 8*5*2)",
    "required":1,
    "school":"MAES",
    "grade":"4"
  },
  {"pack":48,
    "name": "Pencils",
    "type": "pencils",
    "desc":"Pre-sharpened, any type",
    "required":1,
    "school":"MAES",
    "grade":"4"
  },
  {"pack":1,
    "name": "Highlighters",
    "type": "highlighters",
    "desc":"Different colors",
    "required":2,
    "school":"MAES",
    "grade":"4"
  },
  {"pack":12,
    "name": "Colored Pencils",
    "type": "colored_pencils",
    "desc":"12 or 24 pack",
    "required":1,
    "school":"MAES",
    "grade":"4"
  },
  {"pack":12,
    "name": "Markers",
    "type": "markers",
    "desc":"",
    "required":1,
    "school":"MAES",
    "grade":"4"
  },
  {"pack":1,
    "name": "Sharpies",
    "type": "markers",
    "desc":"black only",
    "required":2,
    "school":"MAES",
    "grade":"4"
  },
  {"pack":1,
    "name": "Dry Erase Markers",
    "type": "dry_erase_markers",
    "desc":"black only",
    "required":8,
    "school":"MAES",
    "grade":"4"
  },
  {"pack":24,
    "name": "Crayons",
    "type": "crayons",
    "desc":"Crayola, 24-count or higher",
    "required":1,
    "school":"MAES",
    "grade":"4"
  },
  {"pack":1,
    "name": "Glue Sticks",
    "type": "glue",
    "desc":"",
    "required":4,
    "school":"MAES",
    "grade":"4"
  },
  {"pack":1,
    "name": "Scissors",
    "type": "scissors",
    "desc":"",
    "required":1,
    "school":"MAES",
    "grade":"4"
  },
  {"pack":1,
    "name": "Toothbrush Holder",
    "type": "other",
    "desc":"Travel size, as a pencil holder",
    "required":1,
    "school":"MAES",
    "grade":"4"
  },
  {"pack":1,
    "name": "Notebooks",
    "type": "notebooks",
    "desc":"Wide ruled, spiral, 4 different colors",
    "required":4,
    "school":"MAES",
    "grade":"4"
  },
  {"pack":1,
    "name": "Folder",
    "type": "folders",
    "desc":"Take-home, any color",
    "required":4,
    "school":"MAES",
    "grade":"4"
  },
  {"pack":4,
    "name": "Colored Folders",
    "type": "folders",
    "desc":"Red, Green, Yellow, and Blue.",
    "required":1,
    "school":"MAES",
    "grade":"4"
  },
  {"pack":1,
    "name": "Tennis Shoes",
    "type": "other",
    "desc":"For phy. ed.",
    "required":1,
    "school":"MAES",
    "grade":"4"
  },
  {"pack":1,
    "name": "Computer Mouse",
    "type": "other",
    "desc":"(Recommended), MUST be wireless",
    "required":1,
    "school":"MAES",
    "grade":"4"
  },
  {"pack":200,
    "name": "Kleenex",
    "type": "other",
    "desc":"",
    "required":1,
    "school":"MAES",
    "grade":"4"
  },
  {"pack":1,
    "name": "Bleach Wipes",
    "type": "other",
    "desc":"Clorox",
    "required":3,
    "school":"MAES",
    "grade":"4"
  },
  {"pack":1,
    "name": "Backpack",
    "type": "backpacks",
    "desc":"Not required for all students",
    "required":1,
    "school":"MAES",
    "grade":"3"
  },
  {"pack":1,
    "name": "Headphones/earbuds",
    "type": "headphones",
    "desc":"Good quality, NOT BLUETOOTH",
    "required":1,
    "school":"MAES",
    "grade":"3"
  },
  {"pack":1,
    "name": "School Box",
    "type": "boxes",
    "desc":"Average size, 8*5*2",
    "required":1,
    "school":"MAES",
    "grade":"3"
  },
  {"pack":24,
    "name": "Pencils",
    "type": "pencils",
    "desc":"#2, Sharpened, Yellow Ticonderoga only",
    "required":1,
    "school":"MAES",
    "grade":"3"
  },
  {"pack":1,
    "name": "Whiteboard Eraser",
    "type": "erasers",
    "desc":"",
    "required":1,
    "school":"MAES",
    "grade":"3"
  },
  {"pack":1,
    "name": "Highlighters",
    "type": "highlighters",
    "desc":"Different colors",
    "required":2,
    "school":"MAES",
    "grade":"3"
  },
  {"pack":12,
    "name": "Colored Pencils",
    "type": "colored_pencils",
    "desc":"12 or 24 pack",
    "required":1,
    "school":"MAES",
    "grade":"3"
  },
  {"pack":10,
    "name": "Markers",
    "type": "markers",
    "desc":"Crayola 10-pack",
    "required":1,
    "school":"MAES",
    "grade":"3"
  },
  {"pack":1,
    "name": "Sharpies",
    "type": "markers",
    "desc":"black only",
    "required":4,
    "school":"MAES",
    "grade":"3"
  },
  {"pack":1,
    "name": "Dry Erase Markers",
    "type": "dry_erase_markers",
    "desc":"black only",
    "required":12,
    "school":"MAES",
    "grade":"3"
  },
  {"pack":1,
    "name": "Crayons",
    "type": "crayons",
    "desc":"24-pack",
    "required":1,
    "school":"MAES",
    "grade":"3"
  },
  {"pack":1,
    "name": "Watercolor Paints",
    "type": "other",
    "desc":"",
    "required":1,
    "school":"MAES",
    "grade":"3"
  },
  {"pack":1,
    "name": "Glue Sticks",
    "type": "glue",
    "desc":"",
    "required":10,
    "school":"MAES",
    "grade":"3"
  },
  {"pack":1,
    "name": "Notebook",
    "type": "notebooks",
    "desc":"Wide ruled, composition",
    "required":1,
    "school":"MAES",
    "grade":"3"
  },
  {"pack":4,
    "name": "Notebooks",
    "type": "notebooks",
    "desc":"Wide ruled, spiral, 4 different colors",
    "required":1,
    "school":"MAES",
    "grade":"3"
  },
  {"pack":1,
  "name": "3-Ring Binder",
  "type": "binders",
  "desc":"1-inch, with front cover pocket",
  "required":1,
  "school":"MAES",
  "grade":"3"
  },
  {"pack":4,
    "name": "Colored Folders",
    "type": "folders",
    "desc":"Red, Green, Yellow, and Blue.",
    "required":1,
    "school":"MAES",
    "grade":"3"
  },
  {"pack":30,
    "name": "Page Protectors",
    "type": "other",
    "desc":"Plastic",
    "required":1,
    "school":"MAES",
    "grade":"3"
  },
  {"pack":1,
    "name": "Tennis Shoes",
    "type": "other",
    "desc":"For phy. ed.",
    "required":1,
    "school":"MAES",
    "grade":"3"
  },
  {"pack":1,
    "name": "Backpack",
    "type": "backpacks",
    "desc":"Not required for all students",
    "required":1,
    "school":"MAES",
    "grade":"2"
  },
  {"pack":1,
    "name": "Headphones",
    "type": "headphones",
    "desc":"NOT EARBUDS",
    "required":1,
    "school":"MAES",
    "grade":"2"
  },
  {"pack":24,
    "name": "Pencils",
    "type": "pencils",
    "desc":"#2, Sharpened, Yellow Ticonderoga only",
    "required":1,
    "school":"MAES",
    "grade":"2"
  },
  {"pack":1,
    "name": "Highlighter",
    "type": "highlighters",
    "desc":"Any color",
    "required":1,
    "school":"MAES",
    "grade":"2"
  },
  {"pack":24,
    "name": "Colored Pencils",
    "type": "colored_pencils",
    "desc":"24 or 36 ct.",
    "required":1,
    "school":"MAES",
    "grade":"2"
  },
  {"pack":100,
    "name": "Page Protectors",
    "type": "other",
    "desc":"Plastic",
    "required":1,
    "school":"MAES",
    "grade":"2"
  },
  {"pack":10,
    "name": "Markers",
    "type": "markers",
    "desc":"Crayola, 10 ct.",
    "required":1,
    "school":"MAES",
    "grade":"2"
  },
  {"pack":1,
    "name": "Sharpies",
    "type": "markers",
    "desc":"black only",
    "required":2,
    "school":"MAES",
    "grade":"2"
  },
  {"pack":1,
    "name": "Dry Erase Markers",
    "type": "dry_erase_markers",
    "desc":"Expo only, black",
    "required":6,
    "school":"MAES",
    "grade":"2"
  },
  {"pack":16,
    "name": "Crayons",
    "type": "crayons",
    "desc":"Crayola",
    "required":1,
    "school":"MAES",
    "grade":"2"
  },
  {"pack":1,
    "name": "Watercolor Paints",
    "type": "other",
    "desc":"Crayola",
    "required":1,
    "school":"MAES",
    "grade":"2"
  },
  {"pack":1,
    "name": "Glue Sticks",
    "type": "glue",
    "desc":"",
    "required":8,
    "school":"MAES",
    "grade":"2"
  },
  {"pack":1,
    "name": "Scissors",
    "type": "scissors",
    "desc":"Safety",
    "required":1,
    "school":"MAES",
    "grade":"2"
  },
  {"pack":1,
    "name": "Notebook",
    "type": "notebooks",
    "desc":"Wide-ruled, spiral",
    "required":1,
    "school":"MAES",
    "grade":"2"
  },
  {"pack":1,
    "name": "3-Ring Binder",
    "type": "binders",
    "desc":"",
    "required":1,
    "school":"MAES",
    "grade":"2"
  },
  {"pack":1,
    "name": "Folder",
    "type": "folders",
    "desc":"Plastic prong folder, red",
    "required":1,
    "school":"MAES",
    "grade":"2"
  },
  {"pack":1,
    "name": "Folder",
    "type": "folders",
    "desc":"Plastic prong folder, blue",
    "required":1,
    "school":"MAES",
    "grade":"2"
  },
  {"pack":1,
    "name": "Tennis Shoes",
    "type": "other",
    "desc":"For phy. ed.",
    "required":1,
    "school":"MAES",
    "grade":"2"
  },
  {"pack":200,
    "name": "Kleenex",
    "type": "other",
    "desc":"",
    "required":1,
    "school":"MAES",
    "grade":"2"
  },
  {"pack":1,
    "name": "Bleach Wipes",
    "type": "other",
    "desc":"Clorox",
    "required":1,
    "school":"MAES",
    "grade":"2"
  },
  {"pack":1,
    "name": "Backpack",
    "type": "backpacks",
    "desc":"NO WHEELS!!! Not required for all students",
    "required":1,
    "school":"MAES",
    "grade":"1"
  },
  {"pack":1,
    "name": "Headphones",
    "type": "headphones",
    "desc":"NOT EARBUDS",
    "required":1,
    "school":"MAES",
    "grade":"1"
  },
  {"pack":1,
    "name": "Pencil Box",
    "type": "boxes",
    "desc":"Plastic, regular size, labeled",
    "required":1,
    "school":"MAES",
    "grade":"1"
  },
  {"pack":24,
    "name": "Pencils",
    "type": "pencils",
    "desc":"#2, Sharpened, Yellow Ticonderoga only",
    "required":1,
    "school":"MAES",
    "grade":"1"
  },
  {"pack":1,
    "name": "Highlighter",
    "type": "highlighters",
    "desc":"Yellow",
    "required":1,
    "school":"MAES",
    "grade":"1"
  },
  {"pack":10,
    "name": "Markers",
    "type": "markers",
    "desc":"Crayola classic colors, regular size",
    "required":1,
    "school":"MAES",
    "grade":"1"
  },
  {"pack":1,
    "name": "Dry Erase Markers",
    "type": "dry_erase_markers",
    "desc":"",
    "required":4,
    "school":"MAES",
    "grade":"1"
  },
  {"pack":24,
    "name": "Crayons",
    "type": "crayons",
    "desc":"Crayola",
    "required":1,
    "school":"MAES",
    "grade":"1"
  },
  {"pack":1,
    "name": "Watercolor Paints",
    "type": "other",
    "desc":"Crayola",
    "required":1,
    "school":"MAES",
    "grade":"1"
  },
  {"pack":1,
    "name": "Glue Sticks",
    "type": "glue",
    "desc":"",
    "required":12,
    "school":"MAES",
    "grade":"1"
  },
  {"pack":1,
    "name": "Elmer's White Glue",
    "type": "glue",
    "desc":"",
    "required":1,
    "school":"MAES",
    "grade":"1"
  },
  {"pack":1,
    "name": "Scissors",
    "type": "scissors",
    "desc":"",
    "required":1,
    "school":"MAES",
    "grade":"1"
  },
  {"pack":1,
    "name": "Notebook",
    "type": "notebooks",
    "desc":"Wide ruled, spiral",
    "required":1,
    "school":"MAES",
    "grade":"1"
  },
  {"pack":1,
    "name": "3-Ring Binder",
    "type": "binders",
    "desc":"White, 1-inch",
    "required":1,
    "school":"MAES",
    "grade":"1"
  },
  {"pack":1,
    "name": "Folder",
    "type": "folders",
    "desc":"Red, pocket folder",
    "required":1,
    "school":"MAES",
    "grade":"1"
  },
  {"pack":1,
    "name": "Folder",
    "type": "folders",
    "desc":"Blue, pocket folder",
    "required":1,
    "school":"MAES",
    "grade":"1"
  },
  {"pack":1,
    "name": "Tennis Shoes",
    "type": "other",
    "desc":"For phy. ed.",
    "required":1,
    "school":"MAES",
    "grade":"1"
  },
  {"pack":200,
    "name": "Kleenex",
    "type": "other",
    "desc":"",
    "required":3,
    "school":"MAES",
    "grade":"1"
  },
  {"pack":1,
    "name": "Bleach Wipes",
    "type": "other",
    "desc":"Clorox",
    "required":2,
    "school":"MAES",
    "grade":"1"
  },
  {"pack":1,
    "name": "Backpack",
    "type": "backpacks",
    "desc":"Not required for all students",
    "required":1,
    "school":"MAES",
    "grade":"K"
  },
  {"pack":1,
    "name": "Headphones/earbuds",
    "type": "headphones",
    "desc":"NOT EARBUDS OR BLUETOOTH",
    "required":1,
    "school":"MAES",
    "grade":"K"
  },
  {"pack":12,
    "name": "Pencils",
    "type": "pencils",
    "desc":"#2, Sharpened, Yellow Ticonderoga only",
    "required":1,
    "school":"MAES",
    "grade":"K"
  },
  {"pack":1,
    "name": "Dry Erase Markers",
    "type": "dry_erase_markers",
    "desc":"black only",
    "required":6,
    "school":"MAES",
    "grade":"K"
  },
  {"pack":24,
    "name": "Crayons",
    "type": "crayons",
    "desc":"Crayola",
    "required":1,
    "school":"MAES",
    "grade":"K"
  },
  {"pack":10,
    "name": "Markers",
    "type": "markers",
    "desc":"Crayola",
    "required":1,
    "school":"MAES",
    "grade":"K"
  },
  {"pack":8,
    "name": "Watercolor Paints",
    "type": "other",
    "desc":"Crayola, washable",
    "required":1,
    "school":"MAES",
    "grade":"K"
  },
  {"pack":1,
    "name": "Glue Sticks",
    "type": "glue",
    "desc":"",
    "required":6,
    "school":"MAES",
    "grade":"K"
  },
  {"pack":1,
    "name": "Scissors",
    "type": "scissors",
    "desc":"Fiskars blunt tip, kid",
    "required":1,
    "school":"MAES",
    "grade":"K"
  },
  {"pack":1,
    "name": "Notebooks",
    "type": "notebooks",
    "desc":"Wide ruled, 70 sheets",
    "required":2,
    "school":"MAES",
    "grade":"K"
  },
  {"pack":1,
    "name": "Folder",
    "type": "folders",
    "desc":"Red plastic, 3 prong folder, NOT BINDER",
    "required":1,
    "school":"MAES",
    "grade":"K"
  },
  {"pack":1,
    "name": "Folder",
    "type": "folders",
    "desc":"Blue plastic, 3 prong folder, NOT BINDER",
    "required":1,
    "school":"MAES",
    "grade":"K"
  }
]
